smp25519/__init__.py
smp25519/smp25519.py
smp25519-1.0.0.dist-info/LICENSE
smp25519-1.0.0.dist-info/METADATA
smp25519-1.0.0.dist-info/WHEEL
smp25519-1.0.0.dist-info/top_level.txt
smp25519-1.0.0.dist-info/RECORD
