Metadata-Version: 2.2
Name: smp25519
Version: 1.0.0
Summary: Secure Messaging Protocol 25519
Home-page: https://github.com/979st/smp25519-python
License: Unlicense
Keywords: python,sockets,udp,secure,x25519,blake3,chacha20,protocol,messaging
License-File: LICENSE
Requires-Dist: cryptography>=44.0.0
Requires-Dist: blake3>=1.0.2
Requires-Dist: pycryptodomex>=3.21.0
Dynamic: description
Dynamic: description-content-type
Dynamic: home-page
Dynamic: keywords
Dynamic: license
Dynamic: requires-dist
Dynamic: summary
